nekore/__init__.py
nekore/calculations/__init__.py
nekore/calculations/accounting_processor.py
nekore/calculations/apartment_strategy.py
nekore/calculations/direct_invoice_strategy.py
nekore/calculations/floor_area_strategy.py
nekore/calculations/invoice_collection_processor.py
nekore/calculations/resident_number_strategy.py
nekore/document/__init__.py
nekore/document/assets/__init__.py
nekore/document/assets/top_ornament.png
nekore/document/assets/top_ornament.svg
nekore/document/document_generator.py
nekore/document/document_template.py
nekore/models/__init__.py
nekore/models/accounting.py
nekore/models/allocation_item.py
nekore/models/allocation_strategy.py
nekore/models/apartment.py
nekore/models/bank_account.py
nekore/models/building.py
nekore/models/contact.py
nekore/models/invoice.py
nekore/models/invoice_collection.py
nekore/models/labor_cost_item.py
nekore/models/tenant.py
nekore/models/time_period.py
nekore/py.typed
nekore-1.1.2.dist-info/METADATA
nekore-1.1.2.dist-info/WHEEL
nekore-1.1.2.dist-info/RECORD
